[{"name":"sql.active_record","payload":{"sql":"PRAGMA table_info(\"food_items\")","name":"SCHEMA","connection_id":70344719047360,"statement_name":null,"binds":[],"line":17,"filename":"/Users/nate/Google Drive/WDI/BDD/app/controllers/food_items_controller.rb","method":"new"},"time":"2014-10-22T15:30:25.754+08:00","transaction_id":"3021d28fb27d8af98ccd","end":"2014-10-22T15:30:25.754+08:00","children":[],"duration":0.155},{"name":"sql.active_record","payload":{"sql":"          SELECT name\n          FROM sqlite_master\n          WHERE type = 'table' AND NOT name = 'sqlite_sequence'\n AND name = \"food_items\"","name":"SCHEMA","connection_id":70344719047360,"statement_name":null,"binds":[],"line":17,"filename":"/Users/nate/Google Drive/WDI/BDD/app/controllers/food_items_controller.rb","method":"new"},"time":"2014-10-22T15:30:25.756+08:00","transaction_id":"3021d28fb27d8af98ccd","end":"2014-10-22T15:30:25.756+08:00","children":[],"duration":0.175},{"name":"sql.active_record","payload":{"sql":"PRAGMA table_info(\"food_items\")","name":"SCHEMA","connection_id":70344719047360,"statement_name":null,"binds":[],"line":17,"filename":"/Users/nate/Google Drive/WDI/BDD/app/controllers/food_items_controller.rb","method":"new"},"time":"2014-10-22T15:30:25.757+08:00","transaction_id":"3021d28fb27d8af98ccd","end":"2014-10-22T15:30:25.757+08:00","children":[],"duration":0.14400000000000002},{"name":"render_partial.action_view","payload":{"identifier":"/Users/nate/Google Drive/WDI/BDD/app/views/food_items/_form.html.erb"},"time":"2014-10-22T15:30:25.765+08:00","transaction_id":"bf1ce190ca2eba9bd21a","end":"2014-10-22T15:30:25.788+08:00","children":[],"duration":23.022000000000002},{"name":"render_template.action_view","payload":{"identifier":"/Users/nate/Google Drive/WDI/BDD/app/views/food_items/new.html.erb","layout":"layouts/application"},"time":"2014-10-22T15:30:25.761+08:00","transaction_id":"bf1ce190ca2eba9bd21a","end":"2014-10-22T15:30:25.789+08:00","children":[],"duration":28.494},{"name":"process_action.action_controller","payload":{"controller":"FoodItemsController","action":"new","params":{"action":"new","controller":"food_items"},"format":"html","method":"GET","path":"/food_items/new","status":200,"view_runtime":80.11500000000001,"db_runtime":0.434},"time":"2014-10-22T15:30:25.753+08:00","transaction_id":"bf1ce190ca2eba9bd21a","end":"2014-10-22T15:30:25.839+08:00","children":[],"duration":86.01899999999999}]